masterthesis/__init__.py
masterthesis/beta_decay.py
masterthesis/beta_decay_jit.py
masterthesis/beta_gen.py
masterthesis/cockpit.py
masterthesis/constants.py
masterthesis/dataset.py
masterthesis/fitting.py
masterthesis/model_eval.py
masterthesis/model_pipeline.py
masterthesis/models.py
LucaFallboehmerMasterthesis-0.0.6.dist-info/LICENSE
LucaFallboehmerMasterthesis-0.0.6.dist-info/METADATA
LucaFallboehmerMasterthesis-0.0.6.dist-info/WHEEL
LucaFallboehmerMasterthesis-0.0.6.dist-info/top_level.txt
LucaFallboehmerMasterthesis-0.0.6.dist-info/RECORD
