Metadata-Version: 2.1
Name: LucaFallboehmerMasterthesis
Version: 0.0.6
Summary: Data generation and sensitivity analysis framework for the sterile neutrino search using neural networks. Developed for the TRISTAN Experiment.
Home-page: https://github.com/lucafally/masterthesis
Author: Luca Fallböhmer
Author-email: luca.fallboehmer@tum.de
Requires-Python: >=3.9
License-File: LICENSE
